iunets/__init__.py
iunets/baseline_networks.py
iunets/cayley.py
iunets/expm.py
iunets/householder.py
iunets/layers.py
iunets/networks.py
iunets/utils.py
iunets-0.1.dist-info/LICENSE
iunets-0.1.dist-info/METADATA
iunets-0.1.dist-info/WHEEL
iunets-0.1.dist-info/top_level.txt
iunets-0.1.dist-info/RECORD
